{
  "swagger": "2.0",
  "info": {
    "title": "Users API",
    "description": "Users API",
    "version": "1.0.0"
  },
  "host": "cse341-1-fejf.onrender.com",
  "basePath": "/",
  "schemes": [
    "https"
  ],
  "paths": {
    "/contacts/": {
      "get": {
        "tags": [
          "Contacts"
        ],
        "description": "",
        "produces": [
          "application/json"
        ],
        "responses": {
          "200": {
            "description": "OK"
          },
          "500": {
            "description": "Internal Server Error"
          }
        }
      },
      "post": {
        "tags": [
          "Contacts"
        ],
        "description": "",
        "responses": {
          "201": {
            "description": "Created"
          },
          "500": {
            "description": "Internal Server Error"
          }
        }
      }
    },
    "/contacts/{id}": {
      "get": {
        "tags": [
          "Contacts"
        ],
        "description": "",
        "produces": [
          "application/json"
        ],
        "parameters": [
          {
            "name": "id",
            "in": "path",
            "required": true,
            "type": "string"
          }
        ],
        "responses": {
          "200": {
            "description": "OK"
          },
          "404": {
            "description": "Not Found"
          },
          "500": {
            "description": "Internal Server Error"
          }
        }
      },
      "delete": {
        "tags": [
          "Contacts"
        ],
        "description": "",
        "parameters": [
          {
            "name": "id",
            "in": "path",
            "required": true,
            "type": "string"
          }
        ],
        "responses": {
          "200": {
            "description": "OK"
          },
          "404": {
            "description": "Not Found"
          },
          "500": {
            "description": "Internal Server Error"
          }
        }
      }
    }
  }
}
